download_artifacts.py
gitlab_download_artifacts-1.4.dist-info/LICENSE
gitlab_download_artifacts-1.4.dist-info/METADATA
gitlab_download_artifacts-1.4.dist-info/WHEEL
gitlab_download_artifacts-1.4.dist-info/entry_points.txt
gitlab_download_artifacts-1.4.dist-info/top_level.txt
gitlab_download_artifacts-1.4.dist-info/RECORD
