Metadata-Version: 2.1
Name: gitlab-download-artifacts
Version: 1.4
Summary: Download the gitlab artifacts matching a git repo or submodule, or provided repo http url (optionally with @<commit>)
Home-page: https://gitlab.com/alelec/gitlab-download-artifacts
Author: Andrew Leech
Author-email: andrew@alelec.net
License: MIT
License-File: LICENSE
